{"success":true,"rows":[{"":"МЭР","Дата мониторинга":"2025-08-15T21:00:00.000Z","Мобилизация трудовых ресурсов":"70","Строительная готовность":35,"Конструктив":82,"Устройство котлована (включая шпунтовое ограждение, бермы, откосы, подпорные стены, систему водоотведения дождевых стоков)":"","Устройство фундамента (включая свайное поле, бетонную подготовку, фундаментную плиту)":"","устройство ж/б конструкций":"","Устройство конструкций кровли (подстилающие слои, утеплитель, иные внутренние изоляционные материалы, финишный изоляционный материал)":"","СТЕНЫ И ПЕРЕГОРОДКИ":62.9,"Наружные стены":"","Внутренние перегородки":"","ФАСАДЫ":34.9,"Утеплитель":"","Подсистема фасада":"","Навесные элементы фасада (плитка, панели, другое)":"","Заполнение проемов (окна, двери, другое)":"","Отделочные работы":5.1,"Черновая отделка":12.6,"Пол":"","Стены":"","Потолок (обеспыливание, окрашивание)":"","Монтаж металлических дверей (МОП, инж. помещения и др)":"","Чистовая отделка":0.2,"Потолок":"","Монтаж дверей, наличников, фурнитуры":"","Внутренние инженерные системы":0.9,"Вентиляция":0.8,"ПД, ДУ:":"","Воздуховоды":"","Венттляционные установки, монтаж клапанов":"","ОБЩЕОБМЕННАЯ И ВЫТЯЖНАЯ ВЕНТИЛЯЦИЯ:":"","Вентиляционные установки":"","ПНР с автоматизацией":"","Электрика":0.4,"ГРЩ, ЩИТОВЫЕ:":"","Монтаж щитов, шкафов, лотков, укладка кабеля":"","НАДЗЕМНАЯ/ПОДЗЕМНАЯ ЧАСТЬ:":"","Монтаж лотковых трасс (горизонт, вертикаль)":"","Прокладка кабеля, монтаж щитов и шкафов с расключением":"","Монтаж оконечных устройств с расключением":"","ПНР с получением акта лабораторных испытаний":"","СКС":0.9,"СЕРВЕРНАЯ, КРОССОВЫЕ ПОМЕЩЕНИЯ:":"","Монтаж стоек, АРМ, шкафов":"","Прокладка и расключение кабеля":"","Прокладка кабеля, монтаж и расключение оконечных устройств":"","ПНР":"","Сантехника":1.7,"МОНТАЖ НАСОСНОЙ СТАНЦИИ ПОЖАРОТУШЕНИЯ:":"","Монтаж насосной станции с обвязкой и расключением по ЭОМ и СС":"","ПНР, проверка работоспособности в составе комплексных испытаний":"","Монтаж трубопроводов с запорной арматурой, гребенками и прочего оборудования":"","Монтаж оконечных устройств (радиатор отопления, счетчик, унитаз, раковина, ванная, смесители и т.д.)":"","ЛИФТЫ":1.1,"Механомонтаж":"","ПНР, связь с лифтами, отработка по комплексным испытаниям":"","Наружные инженерные сети":23.9,"Электроснабжение":"","Монтаж ТП":"","Прокладка кабельных линий до ТП (10 кВ)":"","Прокладка кабельных линий (от ТП до ГРЩ)":"","Технилогическое присоединение с получением актов":"","Водоснабжение":"","Наружные сети водопровода в пределах ГПЗУ с учетом ввода в водомерный узел":"","Водомерный узел монтаж":"","Технологическое присоединение с получением актов":"","Теплоснабжение":"","Наружные сети теплоснабжения в пределах ГПЗУ с учетом ввода в ИТП":"","ИТП. Монтаж трубопроводов, технологического оборудования":"","ИТП. Гидравлика, автоматизация (расключение шкафов ЭОМ и СС), окожушивание":"","Технологическое присоединение (МОЭК), Получение акта Ростехнадзора":"","Ливневая канализация":"","Наружные сети ливневой канализации в пределах ГПЗУ":"","Хозяйственно-бытовая канализация":"","Сети хоз. быт. канализации в пределах ГПЗУ":"","Технологическое присоединение":"","Слаботочные сети":"","Сигнал: \"01\"; ГоЧС; \"02\"; ростелеком (подключение и получение справок)":"","БЛАГОУСТРОЙСТВО ПРИЛЕГАЮЩЕЙ ТЕРРИТОРИИ":3.2,"Твердое покрытие":2.4,"Озеленение":2.3,"МАФ":4.9,"object_id":114,"monitoring_date":"2025-08-15T21:00:00.000Z","inspector":"Admin","address":"Физкультурно-оздоровительный комплекс с бассейном, пересечение ул. Шипиловской и Орехового проезда \"Акварис\" район Зябликово, пересечение ул. Шипиловской и Орехового пр-да (Ореховый проезд, д.12)","list":"МЭР","personnel":"70","1_overall_readiness":35,"2_structure":82,"2_1_excavation":"","2_2_foundation":"","2_3_rc_structures":"","2_4_roof_structures":"","3_walls_partitions":62.9,"3_1_external_walls":"","3_2_internal_partitions":"","4_facades":34.9,"4_1_insulation":"","4_2_facade_subsystem":"","4_3_facade_elements":"","4_4_openings_fill":"","5_finishing_total":5.1,"5_1_finishing_prelim":12.6,"5_1_1_floor":"","5_1_2_walls":"","5_1_3_ceiling":"","5_1_4_metal_doors":"","5_2_finishing_final":0.2,"5_2_1_floor":"","5_2_2_walls":"","5_2_3_ceiling":"","5_2_4_doors_hardware":"","6_internal_total":0.9,"6_1_ventilation":0.8,"6_1_1_pd_du":"","6_1_2_air_ducts":"","6_1_3_units_valves":"","6_1_4_general_exhaust":"","6_1_5_air_ducts":"","6_1_6_units":"","6_1_7_commissioning_automation":"","6_2_electric":0.4,"6_2_1_main_boards":"","6_2_2_racks_cable":"","6_2_3_above_below":"","6_2_4_trays":"","6_2_5_cable_boards_wiring":"","6_2_6_end_devices_wiring":"","6_2_7_commissioning_lab":"","6_3_sks":0.9,"6_3_1_server_cross":"","6_3_2_racks_arm_cabinets":"","6_3_3_cable_wiring":"","6_3_4_above_below":"","6_3_5_trays":"","6_3_6_cable_end_devices":"","6_3_7_commissioning":"","6_4_water":1.7,"6_4_1_fire_pump_station":"","6_4_2_station_piping_eom_ss":"","6_4_3_commissioning_complex_tests":"","6_4_4_above_below":"","6_4_5_pipelines_valves_manifolds":"","6_4_6_end_devices":"","7_elevators":1.1,"7_1_mech_install":"","7_2_commissioning_integration":"","8_external_networks":23.9,"8_1_power":"","8_1_1_tp_install":"","8_1_2_cable_to_tp_10kv":"","8_1_3_cable_tp_to_main_boards":"","8_1_4_tech_connection_acts":"","8_2_water_supply":"","8_2_1_external_networks_to_meter":"","8_2_2_meter_unit_install":"","8_2_3_tech_connection_acts":"","8_3_heat_supply":"","8_3_1_external_networks_to_itp":"","8_3_2_itp_piping_equipment":"","8_3_3_itp_hydraulics_automation":"","8_3_4_tech_connection_rtn_act":"","8_4_storm_sewer":"","8_4_1_external_networks":"","8_4_2_tech_connection_acts":"","8_5_household_sewer":"","8_5_1_external_networks":"","8_5_2_tech_connection":"","8_6_low_current":"","8_6_1_signal_01_gochs_02_rostelecom":"","9_landscaping":3.2,"9_1_hard_cover":2.4,"9_2_greening":2.3,"9_3_maf":4.9},{"":"МЭР","Дата мониторинга":"2025-09-15T21:00:00.000Z","Мобилизация трудовых ресурсов":"70","Строительная готовность":46,"Конструктив":83,"Устройство котлована (включая шпунтовое ограждение, бермы, откосы, подпорные стены, систему водоотведения дождевых стоков)":"","Устройство фундамента (включая свайное поле, бетонную подготовку, фундаментную плиту)":"","устройство ж/б конструкций":"","Устройство конструкций кровли (подстилающие слои, утеплитель, иные внутренние изоляционные материалы, финишный изоляционный материал)":"","СТЕНЫ И ПЕРЕГОРОДКИ":62.9,"Наружные стены":"","Внутренние перегородки":"","ФАСАДЫ":34.9,"Утеплитель":"","Подсистема фасада":"","Навесные элементы фасада (плитка, панели, другое)":"","Заполнение проемов (окна, двери, другое)":"","Отделочные работы":5.1,"Черновая отделка":12.6,"Пол":"","Стены":"","Потолок (обеспыливание, окрашивание)":"","Монтаж металлических дверей (МОП, инж. помещения и др)":"","Чистовая отделка":0.2,"Потолок":"","Монтаж дверей, наличников, фурнитуры":"","Внутренние инженерные системы":0.9,"Вентиляция":0.8,"ПД, ДУ:":"","Воздуховоды":"","Венттляционные установки, монтаж клапанов":"","ОБЩЕОБМЕННАЯ И ВЫТЯЖНАЯ ВЕНТИЛЯЦИЯ:":"","Вентиляционные установки":"","ПНР с автоматизацией":"","Электрика":0.4,"ГРЩ, ЩИТОВЫЕ:":"","Монтаж щитов, шкафов, лотков, укладка кабеля":"","НАДЗЕМНАЯ/ПОДЗЕМНАЯ ЧАСТЬ:":"","Монтаж лотковых трасс (горизонт, вертикаль)":"","Прокладка кабеля, монтаж щитов и шкафов с расключением":"","Монтаж оконечных устройств с расключением":"","ПНР с получением акта лабораторных испытаний":"","СКС":0.9,"СЕРВЕРНАЯ, КРОССОВЫЕ ПОМЕЩЕНИЯ:":"","Монтаж стоек, АРМ, шкафов":"","Прокладка и расключение кабеля":"","Прокладка кабеля, монтаж и расключение оконечных устройств":"","ПНР":"","Сантехника":1.7,"МОНТАЖ НАСОСНОЙ СТАНЦИИ ПОЖАРОТУШЕНИЯ:":"","Монтаж насосной станции с обвязкой и расключением по ЭОМ и СС":"","ПНР, проверка работоспособности в составе комплексных испытаний":"","Монтаж трубопроводов с запорной арматурой, гребенками и прочего оборудования":"","Монтаж оконечных устройств (радиатор отопления, счетчик, унитаз, раковина, ванная, смесители и т.д.)":"","ЛИФТЫ":1.1,"Механомонтаж":"","ПНР, связь с лифтами, отработка по комплексным испытаниям":"","Наружные инженерные сети":23.9,"Электроснабжение":"","Монтаж ТП":"","Прокладка кабельных линий до ТП (10 кВ)":"","Прокладка кабельных линий (от ТП до ГРЩ)":"","Технилогическое присоединение с получением актов":"","Водоснабжение":"","Наружные сети водопровода в пределах ГПЗУ с учетом ввода в водомерный узел":"","Водомерный узел монтаж":"","Технологическое присоединение с получением актов":"","Теплоснабжение":"","Наружные сети теплоснабжения в пределах ГПЗУ с учетом ввода в ИТП":"","ИТП. Монтаж трубопроводов, технологического оборудования":"","ИТП. Гидравлика, автоматизация (расключение шкафов ЭОМ и СС), окожушивание":"","Технологическое присоединение (МОЭК), Получение акта Ростехнадзора":"","Ливневая канализация":"","Наружные сети ливневой канализации в пределах ГПЗУ":"","Хозяйственно-бытовая канализация":"","Сети хоз. быт. канализации в пределах ГПЗУ":"","Технологическое присоединение":"","Слаботочные сети":"","Сигнал: \"01\"; ГоЧС; \"02\"; ростелеком (подключение и получение справок)":"","БЛАГОУСТРОЙСТВО ПРИЛЕГАЮЩЕЙ ТЕРРИТОРИИ":3.2,"Твердое покрытие":2.4,"Озеленение":2.3,"МАФ":4.9,"object_id":114,"monitoring_date":"2025-09-15T21:00:00.000Z","inspector":"Admin","address":"Физкультурно-оздоровительный комплекс с бассейном, пересечение ул. Шипиловской и Орехового проезда \"Акварис\" район Зябликово, пересечение ул. Шипиловской и Орехового пр-да (Ореховый проезд, д.12)","list":"МЭР","personnel":"70","1_overall_readiness":46,"2_structure":83,"2_1_excavation":"","2_2_foundation":"","2_3_rc_structures":"","2_4_roof_structures":"","3_walls_partitions":62.9,"3_1_external_walls":"","3_2_internal_partitions":"","4_facades":34.9,"4_1_insulation":"","4_2_facade_subsystem":"","4_3_facade_elements":"","4_4_openings_fill":"","5_finishing_total":5.1,"5_1_finishing_prelim":12.6,"5_1_1_floor":"","5_1_2_walls":"","5_1_3_ceiling":"","5_1_4_metal_doors":"","5_2_finishing_final":0.2,"5_2_1_floor":"","5_2_2_walls":"","5_2_3_ceiling":"","5_2_4_doors_hardware":"","6_internal_total":0.9,"6_1_ventilation":0.8,"6_1_1_pd_du":"","6_1_2_air_ducts":"","6_1_3_units_valves":"","6_1_4_general_exhaust":"","6_1_5_air_ducts":"","6_1_6_units":"","6_1_7_commissioning_automation":"","6_2_electric":0.4,"6_2_1_main_boards":"","6_2_2_racks_cable":"","6_2_3_above_below":"","6_2_4_trays":"","6_2_5_cable_boards_wiring":"","6_2_6_end_devices_wiring":"","6_2_7_commissioning_lab":"","6_3_sks":0.9,"6_3_1_server_cross":"","6_3_2_racks_arm_cabinets":"","6_3_3_cable_wiring":"","6_3_4_above_below":"","6_3_5_trays":"","6_3_6_cable_end_devices":"","6_3_7_commissioning":"","6_4_water":1.7,"6_4_1_fire_pump_station":"","6_4_2_station_piping_eom_ss":"","6_4_3_commissioning_complex_tests":"","6_4_4_above_below":"","6_4_5_pipelines_valves_manifolds":"","6_4_6_end_devices":"","7_elevators":1.1,"7_1_mech_install":"","7_2_commissioning_integration":"","8_external_networks":23.9,"8_1_power":"","8_1_1_tp_install":"","8_1_2_cable_to_tp_10kv":"","8_1_3_cable_tp_to_main_boards":"","8_1_4_tech_connection_acts":"","8_2_water_supply":"","8_2_1_external_networks_to_meter":"","8_2_2_meter_unit_install":"","8_2_3_tech_connection_acts":"","8_3_heat_supply":"","8_3_1_external_networks_to_itp":"","8_3_2_itp_piping_equipment":"","8_3_3_itp_hydraulics_automation":"","8_3_4_tech_connection_rtn_act":"","8_4_storm_sewer":"","8_4_1_external_networks":"","8_4_2_tech_connection_acts":"","8_5_household_sewer":"","8_5_1_external_networks":"","8_5_2_tech_connection":"","8_6_low_current":"","8_6_1_signal_01_gochs_02_rostelecom":"","9_landscaping":3.2,"9_1_hard_cover":2.4,"9_2_greening":2.3,"9_3_maf":4.9},{"":"МЭР","Дата мониторинга":"2025-11-16T21:00:00.000Z","Мобилизация трудовых ресурсов":"118","Строительная готовность":80.1,"Конструктив":85.4,"Устройство котлована (включая шпунтовое ограждение, бермы, откосы, подпорные стены, систему водоотведения дождевых стоков)":"","Устройство фундамента (включая свайное поле, бетонную подготовку, фундаментную плиту)":"","устройство ж/б конструкций":"","Устройство конструкций кровли (подстилающие слои, утеплитель, иные внутренние изоляционные материалы, финишный изоляционный материал)":"","СТЕНЫ И ПЕРЕГОРОДКИ":62.9,"Наружные стены":"","Внутренние перегородки":"","ФАСАДЫ":34.9,"Утеплитель":"","Подсистема фасада":"","Навесные элементы фасада (плитка, панели, другое)":"","Заполнение проемов (окна, двери, другое)":"","Отделочные работы":5.1,"Черновая отделка":12.6,"Пол":"","Стены":"","Потолок (обеспыливание, окрашивание)":"","Монтаж металлических дверей (МОП, инж. помещения и др)":"","Чистовая отделка":0.2,"Потолок":"","Монтаж дверей, наличников, фурнитуры":"","Внутренние инженерные системы":0.9,"Вентиляция":0.8,"ПД, ДУ:":"","Воздуховоды":"","Венттляционные установки, монтаж клапанов":"","ОБЩЕОБМЕННАЯ И ВЫТЯЖНАЯ ВЕНТИЛЯЦИЯ:":"","Вентиляционные установки":"","ПНР с автоматизацией":"","Электрика":0.4,"ГРЩ, ЩИТОВЫЕ:":"","Монтаж щитов, шкафов, лотков, укладка кабеля":"","НАДЗЕМНАЯ/ПОДЗЕМНАЯ ЧАСТЬ:":"","Монтаж лотковых трасс (горизонт, вертикаль)":"","Прокладка кабеля, монтаж щитов и шкафов с расключением":"","Монтаж оконечных устройств с расключением":"","ПНР с получением акта лабораторных испытаний":"","СКС":0.9,"СЕРВЕРНАЯ, КРОССОВЫЕ ПОМЕЩЕНИЯ:":"","Монтаж стоек, АРМ, шкафов":"","Прокладка и расключение кабеля":"","Прокладка кабеля, монтаж и расключение оконечных устройств":"","ПНР":"","Сантехника":1.7,"МОНТАЖ НАСОСНОЙ СТАНЦИИ ПОЖАРОТУШЕНИЯ:":"","Монтаж насосной станции с обвязкой и расключением по ЭОМ и СС":"","ПНР, проверка работоспособности в составе комплексных испытаний":"","Монтаж трубопроводов с запорной арматурой, гребенками и прочего оборудования":"","Монтаж оконечных устройств (радиатор отопления, счетчик, унитаз, раковина, ванная, смесители и т.д.)":"","ЛИФТЫ":1.1,"Механомонтаж":"","ПНР, связь с лифтами, отработка по комплексным испытаниям":"","Наружные инженерные сети":23.9,"Электроснабжение":"","Монтаж ТП":"","Прокладка кабельных линий до ТП (10 кВ)":"","Прокладка кабельных линий (от ТП до ГРЩ)":"","Технилогическое присоединение с получением актов":"","Водоснабжение":"","Наружные сети водопровода в пределах ГПЗУ с учетом ввода в водомерный узел":"","Водомерный узел монтаж":"","Технологическое присоединение с получением актов":"","Теплоснабжение":"","Наружные сети теплоснабжения в пределах ГПЗУ с учетом ввода в ИТП":"","ИТП. Монтаж трубопроводов, технологического оборудования":"","ИТП. Гидравлика, автоматизация (расключение шкафов ЭОМ и СС), окожушивание":"","Технологическое присоединение (МОЭК), Получение акта Ростехнадзора":"","Ливневая канализация":"","Наружные сети ливневой канализации в пределах ГПЗУ":"","Хозяйственно-бытовая канализация":"","Сети хоз. быт. канализации в пределах ГПЗУ":"","Технологическое присоединение":"","Слаботочные сети":"","Сигнал: \"01\"; ГоЧС; \"02\"; ростелеком (подключение и получение справок)":"","БЛАГОУСТРОЙСТВО ПРИЛЕГАЮЩЕЙ ТЕРРИТОРИИ":3.2,"Твердое покрытие":2.4,"Озеленение":2.3,"МАФ":4.9,"object_id":114,"monitoring_date":"2025-11-16T21:00:00.000Z","inspector":"Admin","address":"Физкультурно-оздоровительный комплекс с бассейном, пересечение ул. Шипиловской и Орехового проезда \"Акварис\" район Зябликово, пересечение ул. Шипиловской и Орехового пр-да (Ореховый проезд, д.12)","list":"МЭР","personnel":"118","1_overall_readiness":80.1,"2_structure":85.4,"2_1_excavation":"","2_2_foundation":"","2_3_rc_structures":"","2_4_roof_structures":"","3_walls_partitions":62.9,"3_1_external_walls":"","3_2_internal_partitions":"","4_facades":34.9,"4_1_insulation":"","4_2_facade_subsystem":"","4_3_facade_elements":"","4_4_openings_fill":"","5_finishing_total":5.1,"5_1_finishing_prelim":12.6,"5_1_1_floor":"","5_1_2_walls":"","5_1_3_ceiling":"","5_1_4_metal_doors":"","5_2_finishing_final":0.2,"5_2_1_floor":"","5_2_2_walls":"","5_2_3_ceiling":"","5_2_4_doors_hardware":"","6_internal_total":0.9,"6_1_ventilation":0.8,"6_1_1_pd_du":"","6_1_2_air_ducts":"","6_1_3_units_valves":"","6_1_4_general_exhaust":"","6_1_5_air_ducts":"","6_1_6_units":"","6_1_7_commissioning_automation":"","6_2_electric":0.4,"6_2_1_main_boards":"","6_2_2_racks_cable":"","6_2_3_above_below":"","6_2_4_trays":"","6_2_5_cable_boards_wiring":"","6_2_6_end_devices_wiring":"","6_2_7_commissioning_lab":"","6_3_sks":0.9,"6_3_1_server_cross":"","6_3_2_racks_arm_cabinets":"","6_3_3_cable_wiring":"","6_3_4_above_below":"","6_3_5_trays":"","6_3_6_cable_end_devices":"","6_3_7_commissioning":"","6_4_water":1.7,"6_4_1_fire_pump_station":"","6_4_2_station_piping_eom_ss":"","6_4_3_commissioning_complex_tests":"","6_4_4_above_below":"","6_4_5_pipelines_valves_manifolds":"","6_4_6_end_devices":"","7_elevators":1.1,"7_1_mech_install":"","7_2_commissioning_integration":"","8_external_networks":23.9,"8_1_power":"","8_1_1_tp_install":"","8_1_2_cable_to_tp_10kv":"","8_1_3_cable_tp_to_main_boards":"","8_1_4_tech_connection_acts":"","8_2_water_supply":"","8_2_1_external_networks_to_meter":"","8_2_2_meter_unit_install":"","8_2_3_tech_connection_acts":"","8_3_heat_supply":"","8_3_1_external_networks_to_itp":"","8_3_2_itp_piping_equipment":"","8_3_3_itp_hydraulics_automation":"","8_3_4_tech_connection_rtn_act":"","8_4_storm_sewer":"","8_4_1_external_networks":"","8_4_2_tech_connection_acts":"","8_5_household_sewer":"","8_5_1_external_networks":"","8_5_2_tech_connection":"","8_6_low_current":"","8_6_1_signal_01_gochs_02_rostelecom":"","9_landscaping":3.2,"9_1_hard_cover":2.4,"9_2_greening":2.3,"9_3_maf":4.9}]}
